mongodb_demo/__init__.py
mongodb_demo/mongo_crud.py
mongodbconnection-0.0.6.dist-info/LICENSE
mongodbconnection-0.0.6.dist-info/METADATA
mongodbconnection-0.0.6.dist-info/WHEEL
mongodbconnection-0.0.6.dist-info/top_level.txt
mongodbconnection-0.0.6.dist-info/RECORD
